CRISPRbean-0.1.0.data/scripts/CRISPRbean
beige/__init__.py
beige/model.py
beige/plotting/__init__.py
beige/readwrite/__init__.py
CRISPRbean-0.1.0.dist-info/METADATA
CRISPRbean-0.1.0.dist-info/WHEEL
CRISPRbean-0.1.0.dist-info/top_level.txt
CRISPRbean-0.1.0.dist-info/RECORD
