Metadata-Version: 2.1
Name: CRISPRbean
Version: 0.1.0
Summary: CRISPR Base Editing with Acticity Normalization
Home-page: https://github.com/jykr/beige
Author: Jayoung Ryu
Author-email: jayoung_ryu@g.harvard.edu
Classifier: Programming Language :: Python :: 3
Classifier: Operating System :: OS Independent
Requires-Dist: pyro-ppl
Requires-Dist: numpy
Requires-Dist: berets
